SimpleTkMessageBox
