Metadata-Version: 2.1
Name: SimpleTKMessageBox
Version: 0.2.8
Summary: A simple tkinter message box
Author: Gustoon
Author-email: no.email@gmail.com
Classifier: Programming Language :: Python :: 3
Classifier: License :: OSI Approved :: MIT License
Classifier: Operating System :: OS Independent
Requires-Python: >=3.6
Requires-Dist: Pillow
